feliz/__init__.py
feliz/api_tools.py
feliz/auth_tools.py
feliz/file_tools.py
feliz/global_tools.py
feliz/initialware_tools.py
feliz/inspector_tools.py
feliz/middleware_tools.py
feliz/type_tools.py
feliz-0.2.0.dist-info/licenses/LICENSE
feliz-0.2.0.dist-info/METADATA
feliz-0.2.0.dist-info/WHEEL
feliz-0.2.0.dist-info/top_level.txt
feliz-0.2.0.dist-info/RECORD
