Metadata-Version: 2.4
Name: feliz
Version: 0.2.0
Summary: A framework designed to assist in using Flask and conveniently developing RESTful APIs.
Home-page: https://github.com/zenith3092/feliz
Author: Vincent Wu, Linga Chen, Brian Yin
Author-email: zenith3092@gmail.com
License: MIT
Project-URL: Source, https://github.com/zenith3092/feliz
Classifier: Programming Language :: Python :: 3
Classifier: License :: OSI Approved :: MIT License
Classifier: Operating System :: OS Independent
Requires-Python: >=3.9
License-File: LICENSE
Requires-Dist: flask==2.3.2
Requires-Dist: flask-cors==3.0.10
Requires-Dist: flask_jwt_extended==4.5.2
Requires-Dist: bcrypt==4.0.1
Requires-Dist: pyyaml==5.1
Dynamic: author
Dynamic: author-email
Dynamic: classifier
Dynamic: description
Dynamic: description-content-type
Dynamic: home-page
Dynamic: license
Dynamic: license-file
Dynamic: project-url
Dynamic: requires-dist
Dynamic: requires-python
Dynamic: summary
